oxo_pkg/__init__.py
oxo_pkg/oxo.py
oxo_pkg/models/__init__.py
oxo_pkg/models/models.py
oxo_pkg/resources/__init__.py
oxo_pkg/resources/data.py
oxo_pkg/resources/version.md
oxo_pkg/text/__init__.py
oxo_pkg/text/text.py
oxo_pkg/utils/__init__.py
oxo_pkg/utils/methods.py
oxo_pkg-2.1.1.data/scripts/oxo
oxo_pkg-2.1.1.dist-info/LICENSE
oxo_pkg-2.1.1.dist-info/METADATA
oxo_pkg-2.1.1.dist-info/WHEEL
oxo_pkg-2.1.1.dist-info/top_level.txt
oxo_pkg-2.1.1.dist-info/RECORD
