Metadata-Version: 2.1
Name: oxo-pkg
Version: 2.1.1
Summary: naughts and crosses game
Home-page: https://github.com/add-harris/oxo_pkg
Author: Adam Harrison
Author-email: author@example.com
License: UNKNOWN
Platform: UNKNOWN
Classifier: Programming Language :: Python :: 3
Classifier: License :: OSI Approved :: MIT License
Classifier: Operating System :: OS Independent
Requires-Python: >=3.6
